Workbook

Sheet Info_studio
A1: MATERIALE INFORMATIVO SULLO STUDIO
A3: Scheda informativa dello studio:
A4: "Usare le Forma Mentis Networks per mappare le attitudini nei confronti delle discipline STEM"
A6: Gentile partecipante,
A7: La invitiamo a partecipare al nostro studio che mira ad esplorare l’esperienza da Lei vissuta in quanto
A8: studente o studentessa di discipline STEM.
A10: Scopo dello studio: Lo scopo di questo studio è quello di comprendere le sue esperienze e i suoi processi
A11: cognitivi come studenti e studentesse di discipline STEM.
A13: Sponsorizzazione: Questo studio non è sponsorizzato da enti esterni.
A15: Durata e frequenza: La sua partecipazione comporterà la compilazione di alcuni questionari e l’esecuzione
A16: di tre task. Il tutto non durerà più di 60 minuti.
A18: Descrizione del processo e del compito: Le verrà chiesto di effettuare alcuni compiti, tra cui la
... A44: Assegnista di ricerca dell'Università di Trento

Sheet Consenso_Informato
B1: CONSENSO INFORMATO alla RICERCA
B3: Progetto: “Usare le Forma Mentis Networks per mappare le attitudini nei confronti delle discipline STEM”
A5: Con la presente dichiaro
A6: • di aver letto il foglio informativo sullo studio dal titolo: "Usare le Forma Mentis Networks per mappare le attitudini nei confronti delle discipline STEM";
A7: • che gli obiettivi, i metodi e i rischi dello studio mi sono stati spiegati chiaramente e dettagliatamente dalla dr. Ciringione
A8: • di aver avuto l'opportunità di esprimere le mie considerazioni e chiedere ulteriori chiarimenti, e che ho avuto il tempo di prendere una decisione ponderata e non richiesta;
A9: • di aver compreso che i dati raccolti qui non hanno alcuna rilevanza clinica, ma saranno raccolti ed analizzati puramente a scopo di ricerca;
A10: • di sapere che posso ritirarmi dallo studio in qualsiasi momento senza dover fornire alcuna spiegazione;
A11: • che il mio consenso a partecipare allo studio sopra menzionato è una decisione libera che non è influenzata da promesse di vantaggi finanziari o di altro tipo o da eventuali obblighi verso il ricercatore responsabile dello studio.
A12: Pertanto, sono informato/a sulle attività pianificate e so come posso partecipare allo studio.
A14: Poiché questo è il caso:
A15: X | B15: DO IL MIO CONSENSO A PARTECIPARE ALLO STUDIO
B16: RIFIUTO DI DARE IL MIO CONSENSO A PARTECIPARE ALLO STUDIO
C18: DATA | D18: 45574
C19: FIRMA | D19: X | E19: (INSERIRE UNA X)

Sheet Dati_Demografici
A2: Risponda per cortesia alle seguenti domande. In caso di cella di risposta di colore grigio, la selezioni e poi scelga la risposta per lei adatta dal menù a discesa.
A5: Dati demografici
A7: Età | B7: 20 | C7: Inserire un numero intero (es. 24)
A9: In quale genere si identifica? | B9: Donna
A11: Sesso Biologico | B11: Femminile
A13: Anno di enrollment/inizio studi universitari | B13: 2023 | C13: Inserire solo l'anno (es. 2021)
A15: Ha già conseguito una laurea? | B15: No
A17: Livello di istruzione più alto di almeno uno dei suoi due genitori | B17: Diploma di scuola superiore secondaria

Sheet Questionari
A4: Come quantificherebbe il suo livello accademico in:
A5: Selezioni la risposta dalla freccetta accanto ciascuna cella di risposta grigia
A7: Materie scientifiche, come chimica, biologia e scienze della vita | B7: 2 - Abilità e competenze limitate
A9: Scienze umanistiche e sociali | B9: 4 - Abilità e competenze superiori alla media
A11: Matematica e fisica | B11: 2 - Abilità e competenze limitate
A13: Coding, programmazione e simulazioni al computer | B13: 1 - Abilità scarse o inesistenti
A18: Descriva in che misura ciascuna di queste affermazioni la descrive
A19: Selezioni la risposta dalla freccetta accanto ciascuna cella di risposta grigia
A20: Self-regulated learning
A22: 1. Preferisco problemi complessi a problemi semplici | B22: 3
A24: 2. Preferisco essere responsabile della gestione di situazioni che richiedono sforzo di pensiero | B24: 5 - Mi descrive molto bene
A26: 3. "Pensare" non è la mia idea di divertimento | B26: 2
A28: 4. Preferirei fare qualcosa che richiede scarsa attività cognitiva piuttosto che qualcosa che sfida la mia capacità di pensiero | B28: 2
A30: 5. Io cerco di anticipare o evitare situazioni in cui probabilmente dovrò pensare a fondo riguardo a qualcosa | B30: 3
A32: 6. Provo soddisfazione nel riflettere molto e a lungo | B32: 5 - Mi descrive molto bene
A34: 7. Io penso solo se sono costretto a farlo | B34: 2
A36: 8. Preferisco pensare a piccoli progetti quotidiani, piuttosto che a progetti a lungo termine | B36: 2
A38: 9. Preferisco compiti che richiedono piccoli sforzi cognitivi dopo essere stati appresi | B38: 3
A40: 10. L'idea di contare sul pensiero per trovare la mia strada mi intriga | B40: 4
A42: 11. Mi piace un compito che prevede l'arrivo a nuove soluzioni per risolvere problemi | B42: 4
A44: 12. Imparare nuovi modi di pensare non mi eccita molto | B44: 2
A46: 13. Preferisco riempire la mia vita con puzzles da risolvere | B46: 2
A48: 14. La nozione di pensiero astrattamente mi affascina | B48: 4
A50: 15. Preferirei un compito intellettuale, difficile e importante rispetto ad uno piuttosto importante ma che non richiede pensiero | B50: 3
A52: 16. Provo sollievo piuttosto che soddisfazione dopo aver completato un compito che ha richiesto una gran quantità di sforzo mentale | B52: 3
A54: 17. E' sufficiente per me ottenere un risultato dal lavoro fatto; non mi curo del come o perchè esso funziona | B54: 1 - Non mi descrive per nulla
A56: 18. Io normalmente finisco per riflettere riguardo a un tema anche se esso non mi riguarda personalmente | B56: 5 - Mi descrive molto bene
A62: Mi vedo come una persona che ...
A63: Motivational Learning | E63: questo corso... cioè??
A64: Selezioni la risposta dalla freccetta accanto ciascuna cella di risposta grigia
A66: 1) ...è riservata | B66: 4
A68: 2) ...generalmente si fida | B68: 3
A70: 3) ...tende a essere pigra | B70: 1 - Per niente d'accordo
A72: 4) ...è rilassata, sopporta bene lo stress | B72: 1 - Per niente d'accordo
A74: 5) ...ha pochi interessi artistici | B74: 4
A76: 6) ...è spigliata, socievole | B76: 3
A78: 7) ...tende a trovare i difetti negli altri | B78: 4
A80: 8) ...è coscienziosa nel lavoro | B80: 5 - Completamente d'accordo
A82: 9) ...si agita facilmente | B82: 5 - Completamente d'accordo
A84: 10) ...ha una fervida immaginazione | B84: 4
A90: Consideriamo ora la seguente serie di situazioni. Quanto si sentirebbe ansiosa/o in questi scenari?
A91: Math anxiety UK
A93: Avere qualcuno che mi guarda moltiplicare 12 x 23 su carta. | B93: 2 - Leggermente ansioso/a
A95: Calcolare la somma degli spiccioli di un resto. | B95: 3 - Moderatamente ansiosa/o
A97: Se mi viene chiesto di scrivere una risposta alla lavagna all'inizio di una lezione di matematica. | B97: 3 - Moderatamente ansiosa/o
A99: Se mi viene chiesto di sommare il numero di persone in una stanza. | B99: 1 - Per niente ansiosa/o
A101: Calcolare quanti giorni mancano al compleanno di una persona. | B101: 1 - Per niente ansiosa/o
A103: Sostenere un esame di matematica. | B103: 3 - Moderatamente ansiosa/o
A105: Se mi viene chiesto davanti a molte altre persone di calcolare EUR 9,36 diviso per 4. | B105: 2 - Leggermente ansioso/a
A107: Ricevere un numero di telefono e doverlo ricordare. | B107: 1 - Per niente ansiosa/o
A109: Leggere la parola "algebra". | B109: 1 - Per niente ansiosa/o
A111: Calcolare una serie di moltiplicazioni su carta. | B111: 1 - Per niente ansiosa/o
A113: Calcolare quanto tempo mi rimane prima di partire per il lavoro o il luogo di studio. | B113: 2 - Leggermente ansioso/a
A115: Ascoltare qualcuno che parla di matematica. | B115: 1 - Per niente ansiosa/o
... A137: Se mi viene chiesta una domanda di matematica da un/una insegnante di fronte alla classe. | B137: 4 - Molto ansioso/a
A142: Per favore, legga ogni frase e poi indichi con quale frequenza la situazione descritta si è verificata negli ultimi sette giorni
A143: Selezioni la risposta dalla freccetta accanto ciascuna cella di risposta grigia
A145: Ho provato molta tensione e ho avuto difficoltà a recuperare uno stato di calma | B145: 3 - Mi è capitato con una certa frequenza
A147: Ho avuto la tendenza a reagire in maniera eccessiva alle situazioni | B147: 3 - Mi è capitato con una certa frequenza
A149: Ho sentito che stavo impiegando molta energia nervosa | B149: 4 - Mi è capitato quasi sempre
A151: Mi sono sentito stressato | B151: 3 - Mi è capitato con una certa frequenza
A153: Ho avuto difficoltà a rilassarmi | B153: 3 - Mi è capitato con una certa frequenza
A155: Non riuscivo a tollerare per nulla eventi o situazioni che mi impedivano di portare avanti ciò che stavo facendo | B155: 3 - Mi è capitato con una certa frequenza
A157: Mi sono sentito piuttosto irritabile | B157: 2 - Mi è capitato qualche volta

Sheet Task_1parte_Associazioni
A1: cue word | C1: association_1 | E1: association_2 | G1: association_3
A2: Consideriamo ora questo gioco di associazione:
J3: ESEMPIO DI COMPILAZIONE - ASSOCIAZIONI
A4: Legga la parola in grassetto e scriva negli spazi grigi le prime 3 parole che le vengono in mente dopo averla letta
A5: Per favore, provi a utilizzare una sola parola come associazione
A6: Non ci sono risposte giuste o sbagliate, cerchi solo di farlo il più velocemente possibile.
A7: Se non ha associazioni, lasci gli spazi vuoti.
A8: Pronto/a?
A10: Quali parole le vengono in mente quando legge:
A11: parola_cue | C11: associazione_1 | E11: associazione_2 | G11: associazione_3
A13: tecnologia | C13: Computer | E13: Telefono | G13: Tecnico informatico
A15: benessere | C15: Spa | E15: Cura personale | G15: Sport
A17: futuro | C17: Incertezza | E17: Preoccupazione
A19: personalità | C19: Timidezza | E19: Determinazione | G19: Generosità
A21: laurea | C21: Triennale | E21: Magistrale | G21: Ad honorem
A23: numeri | C23: Algebra | E23: Matematica | G23: Calcoli
A25: frustrazione | C25: Stress | E25: Problemi
A27: scuola | C27: Amicizie | E27: Verifiche | G27: Interrogazioni
A29: statistica | C29: Dati | E29: Stime | G29: Algebra
A31: fisica | C31: Leggi | E31: Gravità | G31: Massa
A33: compito | C33: Scolastico | E33: Matematico | G33: Scuola
A35: neuroscienze | C35: Cognitive | E35: Psicologia | G35: Magistrale
A37: insegnante | C37: Scuola | E37: Sostegno
A39: sfida | C39: Ostacolo | E39: Obiettivo | G39: Impegno
A41: comportamento | C41: Positivo | E41: Negativo | G41: Sociale
A43: professore | C43: Università | E43: Lezione | G43: Nozioni
A45: stress | C45: Quotidianità | E45: Università | G45: Impegni
A47: creatività | C47: Inventare | E47: Creare | G47: Immaginare
A49: relazione | C49: Stabile | E49: Matura | G49: Felice
A51: ansia | C51: Costanza | E51: Difficoltà | G51: Quotidianità
A53: psicologia | C53: Laurea | E53: Corso | G53: Facoltà
A55: scienza | C55: Psicologia | E55: Fisica | G55: Biologia
A57: terapia | C57: Aiuto | E57: Sostegno | G57: Miglioramento
A59: matematica | C59: Materia | E59: Facoltà | G59: Calcoli
A61: equazione | C61: Calcolo | E61: Valori | G61: Dati
... A69: mente | C69: Cervello | E69: Psicologia | G69: Processi
A71: biologia | C71: Corpo | E71: Animali
A73: curiosità | C73: Interessi | E73: Bambini | G73: Scoperta
A75: conoscenza | C75: Sapienza | E75: Potere | G75: Vantaggio
A77: voto | C77: Numero | E77: Valore | G77: Importanza
A79: noia | C79: Stress | E79: Pensieri | G79: Ansia
A81: scoperta | C81: Novità | E81: Prospettive
A83: esame | C83: Ansia | E83: Determinazione | G83: Impegno
A85: cognizione | C85: Animale | E85: Umana | G85: Comportamento
A87: lavoro | C87: Stipendio | E87: Fatica | G87: Stanchezza
A89: grafico | C89: Dati | E89: Barre | G89: Torta
A91: esercitazione | C91: Prova | E91: Test | G91: Punteggio
A93: studente | C93: Treno | E93: Libri | G93: Lezioni

Sheet Task_2parte_Valenza
A2: Consideriamo ora la valenza emotiva ispirata dai concetti. | J2: ESEMPIO DI COMPILAZIONE - VALENZA
A3: Esprima quanto positivamente o negativamente percepisce ogni concetto, isolatamente, in una scala da 1 a 5
A4: dove 1 sta per "Molto negativo", 3 sta per "Neutrale" e 5 sta per "Molto Positivo".
A5: Scriva il numero negli spazi bianchi successivi alla parola/associazione.
A6: Ricordi di valutare i concetti in base alla sua personale percezione.
A7: ATTENZIONE! NON MODIFICHI LE PAROLE "ASSOCIAZIONE" IN QUESTO FOGLIO!
A9: parola_cue | B9: valenza_cue | C9: associazione_1 | D9: valenza_1 | E9: associazione_2 | F9: valenza_2 | G9: associazione_3 | H9: valenza_3
A11: =Task_1parte_Associazioni!A13 -> tecnologia | B11: 3 | C11: =Task_1parte_Associazioni!C13 -> Computer | D11: 5 | E11: =Task_1parte_Associazioni!E13 -> Telefono | F11: 3 | G11: =Task_1parte_Associazioni!G13 -> Tecnico informatico | H11: 3
A13: =Task_1parte_Associazioni!A15 -> benessere | B13: 5 | C13: =Task_1parte_Associazioni!C15 -> Spa | D13: 5 | E13: =Task_1parte_Associazioni!E15 -> Cura personale | F13: 5 | G13: =Task_1parte_Associazioni!G15 -> Sport | H13: 3
A15: =Task_1parte_Associazioni!A17 -> futuro | B15: 3 | C15: =Task_1parte_Associazioni!C17 -> Incertezza | D15: 3 | E15: =Task_1parte_Associazioni!E17 -> Preoccupazione | F15: 5 | G15: =Task_1parte_Associazioni!G17 -> 0 | H15: =Task_1parte_Associazioni!H17 -> 0
A17: =Task_1parte_Associazioni!A19 -> personalità | B17: 5 | C17: =Task_1parte_Associazioni!C19 -> Timidezza | D17: 3 | E17: =Task_1parte_Associazioni!E19 -> Determinazione | F17: 5 | G17: =Task_1parte_Associazioni!G19 -> Generosità | H17: 5
A19: =Task_1parte_Associazioni!A21 -> laurea | B19: 5 | C19: =Task_1parte_Associazioni!C21 -> Triennale | D19: 5 | E19: =Task_1parte_Associazioni!E21 -> Magistrale | F19: 3 | G19: =Task_1parte_Associazioni!G21 -> Ad honorem | H19: 3
A21: =Task_1parte_Associazioni!A23 -> numeri | B21: 3 | C21: =Task_1parte_Associazioni!C23 -> Algebra | D21: 3 | E21: =Task_1parte_Associazioni!E23 -> Matematica | F21: 3 | G21: =Task_1parte_Associazioni!G23 -> Calcoli | H21: =Task_1parte_Associazioni!H23 -> 0
A23: =Task_1parte_Associazioni!A25 -> frustrazione | B23: =Task_1parte_Associazioni!B25 -> 0 | C23: =Task_1parte_Associazioni!C25 -> Stress | D23: =Task_1parte_Associazioni!D25 -> 0 | E23: =Task_1parte_Associazioni!E25 -> Problemi | F23: 3 | G23: =Task_1parte_Associazioni!G25 -> 0 | H23: =Task_1parte_Associazioni!H25 -> 0
A25: =Task_1parte_Associazioni!A27 -> scuola | B25: 3 | C25: =Task_1parte_Associazioni!C27 -> Amicizie | D25: 5 | E25: =Task_1parte_Associazioni!E27 -> Verifiche | F25: 1 | G25: =Task_1parte_Associazioni!G27 -> Interrogazioni | H25: 1
A27: =Task_1parte_Associazioni!A29 -> statistica | B27: 3 | C27: =Task_1parte_Associazioni!C29 -> Dati | D27: 3 | E27: =Task_1parte_Associazioni!E29 -> Stime | F27: 3 | G27: =Task_1parte_Associazioni!G29 -> Algebra | H27: 3
A29: =Task_1parte_Associazioni!A31 -> fisica | B29: 1 | C29: =Task_1parte_Associazioni!C31 -> Leggi | D29: 3 | E29: =Task_1parte_Associazioni!E31 -> Gravità | F29: 3 | G29: =Task_1parte_Associazioni!G31 -> Massa | H29: 3
A31: =Task_1parte_Associazioni!A33 -> compito | B31: 3 | C31: =Task_1parte_Associazioni!C33 -> Scolastico | D31: 3 | E31: =Task_1parte_Associazioni!E33 -> Matematico | F31: 3 | G31: =Task_1parte_Associazioni!G33 -> Scuola | H31: 3
A33: =Task_1parte_Associazioni!A35 -> neuroscienze | B33: 3 | C33: =Task_1parte_Associazioni!C35 -> Cognitive | D33: 3 | E33: =Task_1parte_Associazioni!E35 -> Psicologia | F33: 5 | G33: =Task_1parte_Associazioni!G35 -> Magistrale | H33: 3
A35: =Task_1parte_Associazioni!A37 -> insegnante | B35: 3 | C35: =Task_1parte_Associazioni!C37 -> Scuola | D35: 3 | E35: =Task_1parte_Associazioni!E37 -> Sostegno | F35: 5 | G35: =Task_1parte_Associazioni!G37 -> 0 | H35: =Task_1parte_Associazioni!H37 -> 0
A37: =Task_1parte_Associazioni!A39 -> sfida | B37: 3 | C37: =Task_1parte_Associazioni!C39 -> Ostacolo | D37: 3 | E37: =Task_1parte_Associazioni!E39 -> Obiettivo | F37: 5 | G37: =Task_1parte_Associazioni!G39 -> Impegno | H37: 5
A39: =Task_1parte_Associazioni!A41 -> comportamento | B39: 3 | C39: =Task_1parte_Associazioni!C41 -> Positivo | D39: 3 | E39: =Task_1parte_Associazioni!E41 -> Negativo | F39: 3 | G39: =Task_1parte_Associazioni!G41 -> Sociale | H39: 3
A41: =Task_1parte_Associazioni!A43 -> professore | B41: 3 | C41: =Task_1parte_Associazioni!C43 -> Università | D41: 3 | E41: =Task_1parte_Associazioni!E43 -> Lezione | F41: 3 | G41: =Task_1parte_Associazioni!G43 -> Nozioni | H41: 5
A43: =Task_1parte_Associazioni!A45 -> stress | B43: 1 | C43: =Task_1parte_Associazioni!C45 -> Quotidianità | D43: 5 | E43: =Task_1parte_Associazioni!E45 -> Università | F43: 3 | G43: =Task_1parte_Associazioni!G45 -> Impegni | H43: 1
A45: =Task_1parte_Associazioni!A47 -> creatività | B45: 3 | C45: =Task_1parte_Associazioni!C47 -> Inventare | D45: 3 | E45: =Task_1parte_Associazioni!E47 -> Creare | F45: 3 | G45: =Task_1parte_Associazioni!G47 -> Immaginare | H45: 5
A47: =Task_1parte_Associazioni!A49 -> relazione | B47: 5 | C47: =Task_1parte_Associazioni!C49 -> Stabile | D47: 5 | E47: =Task_1parte_Associazioni!E49 -> Matura | F47: 5 | G47: =Task_1parte_Associazioni!G49 -> Felice | H47: 5
A49: =Task_1parte_Associazioni!A51 -> ansia | B49: 1 | C49: =Task_1parte_Associazioni!C51 -> Costanza | D49: 3 | E49: =Task_1parte_Associazioni!E51 -> Difficoltà | F49: 3 | G49: =Task_1parte_Associazioni!G51 -> Quotidianità | H49: 3
A51: =Task_1parte_Associazioni!A53 -> psicologia | B51: 5 | C51: =Task_1parte_Associazioni!C53 -> Laurea | D51: 5 | E51: =Task_1parte_Associazioni!E53 -> Corso | F51: 3 | G51: =Task_1parte_Associazioni!G53 -> Facoltà | H51: 3
A53: =Task_1parte_Associazioni!A55 -> scienza | B53: 3 | C53: =Task_1parte_Associazioni!C55 -> Psicologia | D53: 5 | E53: =Task_1parte_Associazioni!E55 -> Fisica | F53: 1 | G53: =Task_1parte_Associazioni!G55 -> Biologia | H53: 5
A55: =Task_1parte_Associazioni!A57 -> terapia | B55: 5 | C55: =Task_1parte_Associazioni!C57 -> Aiuto | D55: 5 | E55: =Task_1parte_Associazioni!E57 -> Sostegno | F55: 5 | G55: =Task_1parte_Associazioni!G57 -> Miglioramento | H55: 5
A57: =Task_1parte_Associazioni!A59 -> matematica | B57: 3 | C57: =Task_1parte_Associazioni!C59 -> Materia | D57: 3 | E57: =Task_1parte_Associazioni!E59 -> Facoltà | F57: 3 | G57: =Task_1parte_Associazioni!G59 -> Calcoli | H57: 3
A59: =Task_1parte_Associazioni!A61 -> equazione | B59: 3 | C59: =Task_1parte_Associazioni!C61 -> Calcolo | D59: 3 | E59: =Task_1parte_Associazioni!E61 -> Valori | F59: 3 | G59: =Task_1parte_Associazioni!G61 -> Dati | H59: 3
... A67: =Task_1parte_Associazioni!A69 -> mente | B67: 3 | C67: =Task_1parte_Associazioni!C69 -> Cervello | D67: 3 | E67: =Task_1parte_Associazioni!E69 -> Psicologia | F67: 3 | G67: =Task_1parte_Associazioni!G69 -> Processi | H67: 3
A69: =Task_1parte_Associazioni!A71 -> biologia | B69: 5 | C69: =Task_1parte_Associazioni!C71 -> Corpo | D69: 3 | E69: =Task_1parte_Associazioni!E71 -> Animali | F69: 5 | G69: =Task_1parte_Associazioni!G71 -> 0 | H69: =Task_1parte_Associazioni!H71 -> 0
A71: =Task_1parte_Associazioni!A73 -> curiosità | B71: 5 | C71: =Task_1parte_Associazioni!C73 -> Interessi | D71: 5 | E71: =Task_1parte_Associazioni!E73 -> Bambini | F71: 3 | G71: =Task_1parte_Associazioni!G73 -> Scoperta | H71: 3
A73: =Task_1parte_Associazioni!A75 -> conoscenza | B73: 5 | C73: =Task_1parte_Associazioni!C75 -> Sapienza | D73: 5 | E73: =Task_1parte_Associazioni!E75 -> Potere | F73: 5 | G73: =Task_1parte_Associazioni!G75 -> Vantaggio | H73: 5
A75: =Task_1parte_Associazioni!A77 -> voto | B75: 3 | C75: =Task_1parte_Associazioni!C77 -> Numero | D75: 3 | E75: =Task_1parte_Associazioni!E77 -> Valore | F75: 5 | G75: =Task_1parte_Associazioni!G77 -> Importanza | H75: 5
A77: =Task_1parte_Associazioni!A79 -> noia | B77: 1 | C77: =Task_1parte_Associazioni!C79 -> Stress | D77: 1 | E77: =Task_1parte_Associazioni!E79 -> Pensieri | F77: 1 | G77: =Task_1parte_Associazioni!G79 -> Ansia | H77: 1
A79: =Task_1parte_Associazioni!A81 -> scoperta | B79: 3 | C79: =Task_1parte_Associazioni!C81 -> Novità | D79: 3 | E79: =Task_1parte_Associazioni!E81 -> Prospettive | F79: 3 | G79: =Task_1parte_Associazioni!G81 -> 0 | H79: =Task_1parte_Associazioni!H81 -> 0
A81: =Task_1parte_Associazioni!A83 -> esame | B81: 1 | C81: =Task_1parte_Associazioni!C83 -> Ansia | D81: 1 | E81: =Task_1parte_Associazioni!E83 -> Determinazione | F81: 5 | G81: =Task_1parte_Associazioni!G83 -> Impegno | H81: 5
A83: =Task_1parte_Associazioni!A85 -> cognizione | B83: 3 | C83: =Task_1parte_Associazioni!C85 -> Animale | D83: 3 | E83: =Task_1parte_Associazioni!E85 -> Umana | F83: 3 | G83: =Task_1parte_Associazioni!G85 -> Comportamento | H83: 3
A85: =Task_1parte_Associazioni!A87 -> lavoro | B85: 3 | C85: =Task_1parte_Associazioni!C87 -> Stipendio | D85: 5 | E85: =Task_1parte_Associazioni!E87 -> Fatica | F85: 3 | G85: =Task_1parte_Associazioni!G87 -> Stanchezza | H85: 1
A87: =Task_1parte_Associazioni!A89 -> grafico | B87: 3 | C87: =Task_1parte_Associazioni!C89 -> Dati | D87: 3 | E87: =Task_1parte_Associazioni!E89 -> Barre | F87: 3 | G87: =Task_1parte_Associazioni!G89 -> Torta | H87: 3
A89: =Task_1parte_Associazioni!A91 -> esercitazione | B89: 1 | C89: =Task_1parte_Associazioni!C91 -> Prova | D89: 1 | E89: =Task_1parte_Associazioni!E91 -> Test | F89: 1 | G89: =Task_1parte_Associazioni!G91 -> Punteggio | H89: 1
A91: =Task_1parte_Associazioni!A93 -> studente | B91: 3 | C91: =Task_1parte_Associazioni!C93 -> Treno | D91: 1 | E91: =Task_1parte_Associazioni!E93 -> Libri | F91: 3 | G91: =Task_1parte_Associazioni!G93 -> Lezioni | H91: 3

Sheet breve_testo
A1: Scriva adesso un breve testo di circa 250 parole relativamente a come si sente quando si trova ad affrontare le discipline STEM.
A2: "Quando affronto le discipline STEM…"
A3: mi sento volenterosa a svolgere il compito per il bene della ricerca. Cerco sempre di impegnarmi e svolgere al meglio delle mie possibilità il compito che mi viene assegnato. Tuttavia, a volte mi sento come se alcune mie risposte non siano quelle più "ottimali" o "giuste" da dare. Ciononostante, penso anche che esseri sinceri e onesti sia la cosa migliore che si possa fare, dato che è inutile dare risposte che non corrispondono alla realtà, in quanto potrebbe compromettere la validità dell'esperimento. Nel complesso, durante il loro svolgimento mi sento rilassata e non provo ansia. Dunque, la reputo un'esperienza positiva, che se non richiedesse così tanto tempo con tutte le probabilità svolgerei più spesso.
